<consolidatedDB><dbType name="SQL"><dbSchema name="ROUTE_DB"><table name="routes"><column name="route_id"><dataType>bigint</dataType><columnKey>PRI</columnKey><references /></column></table><table name="route_timings"><column name="route_no"><dataType>varchar</dataType><columnKey>PRI</columnKey><references /></column></table></dbSchema></dbType><dbType name="CSV"><dbSchema name="gis"><table name="lat_long_stops"><column name="stop"><dataType>object</dataType><columnKey /><references /></column><column name="lat"><dataType>float64</dataType><columnKey /><references /></column><column name="long"><dataType>float64</dataType><columnKey /><references /></column></table></dbSchema><dbSchema name="other details"><table name="route_vehicle_details"><column name="vehicle_no"><dataType>object</dataType><columnKey /><references /></column><column name="schedule_no"><dataType>object</dataType><columnKey /><references /></column><column name="sim_number"><dataType>int64</dataType><columnKey /><references /></column><column name="depot"><dataType>object</dataType><columnKey /><references /></column><column name="last_inserted_tm"><dataType>object</dataType><columnKey /><references /></column></table><table name="schedule_details"><column name="schedule_no"><dataType>object</dataType><columnKey /><references /></column><column name="schedule_name"><dataType>object</dataType><columnKey /><references /></column></table><table name="ticket_details"><column name="ticket_type_id"><dataType>int64</dataType><columnKey /><references /></column><column name="ticket_type_name"><dataType>object</dataType><columnKey /><references /></column><column name="status"><dataType>object</dataType><columnKey /><references /></column><column name="notes"><dataType>object</dataType><columnKey /><references /></column></table><table name="veh_device"><column name="vehicle_no"><dataType>object</dataType><columnKey /><references /></column><column name="device_id"><dataType>object</dataType><columnKey /><references /></column><column name="sim_number"><dataType>int64</dataType><columnKey /><references /></column><column name="depot"><dataType>object</dataType><columnKey /><references /></column></table></dbSchema></dbType></consolidatedDB>